README.md
mf2util.py
setup.cfg
setup.py
mf2util.egg-info/PKG-INFO
mf2util.egg-info/SOURCES.txt
mf2util.egg-info/dependency_links.txt
mf2util.egg-info/top_level.txt