Metadata-Version: 1.1
Name: mf2util
Version: 0.5.1
Summary: Python Microformats2 utilities, a companion to mf2py
Home-page: http://indiewebcamp.com/mf2util
Author: Kyle Mahan
Author-email: kyle@kylewm.com
License: UNKNOWN
Platform: UNKNOWN
Classifier: Development Status :: 3 - Alpha
Classifier: Intended Audience :: Developers
Classifier: License :: OSI Approved :: BSD License
Classifier: Natural Language :: English
Classifier: Programming Language :: Python
Classifier: Programming Language :: Python :: 3
Classifier: Topic :: Text Processing :: Markup :: HTML
